{"cameraMode":{"drawMode":0,"name":"Shaded","section":"Shading Mode"},"sceneLighting":true,"audioPlay":false,"sceneViewState":{"showFog":true,"showMaterialUpdate":false,"showSkybox":true,"showFlares":true,"showImageEffects":true,"showParticleSystems":true},"in2DMode":false,"pivot":{"x":27.942951202392579,"y":8.168859481811524,"z":-13.490364074707032},"rotation":{"x":0.46042951941490176,"y":-0.09552249312400818,"z":0.049927953630685809,"w":0.8811538815498352},"size":21.87014389038086,"orthographic":false}